spacy_download/__init__.py
spacy_download/load.py
spacy_download-1.1.0.dist-info/LICENSE
spacy_download-1.1.0.dist-info/METADATA
spacy_download-1.1.0.dist-info/WHEEL
spacy_download-1.1.0.dist-info/top_level.txt
spacy_download-1.1.0.dist-info/RECORD
