Metadata-Version: 2.1
Name: spacy-download
Version: 1.1.0
Summary: Download and load spaCy models on-the-fly.
Home-page: https://github.com/BramVanroy/spacy_download
Author: Bram Vanroy
Author-email: bramvanroy@hotmail.com
License: MIT
Project-URL: Bug Reports, https://github.com/BramVanroy/spacy_download/issues
Project-URL: Source, https://github.com/BramVanroy/spacy_download
Keywords: nlp spacy spacy-extension
Classifier: Intended Audience :: Developers
Classifier: Intended Audience :: Science/Research
Classifier: Topic :: Scientific/Engineering
Classifier: Topic :: Text Processing
Classifier: Programming Language :: Python :: 3.6
Classifier: Programming Language :: Python :: 3.7
Classifier: Programming Language :: Python :: 3.8
Classifier: Programming Language :: Python :: 3.9
Classifier: Programming Language :: Python :: 3.10
Classifier: Programming Language :: Python :: 3.11
Classifier: Operating System :: OS Independent
Requires-Python: >=3.6
License-File: LICENSE
Requires-Dist: spacy (<4.0.0,>=3.0.0)
Provides-Extra: dev
Requires-Dist: pytest ; extra == 'dev'
Requires-Dist: flake8 ; extra == 'dev'
Requires-Dist: isort ; extra == 'dev'
Requires-Dist: black ; extra == 'dev'
Requires-Dist: pygments ; extra == 'dev'
Requires-Dist: spacy-transformers ; extra == 'dev'
